bix_analysis_libraries/__init__.py
bix_analysis_libraries/bix_standard_functions.py
bix_analysis_libraries/plotly.py
bix_analysis_libraries/thot.py
bix_analysis_libraries/dark_bias/__init__.py
bix_analysis_libraries/dark_bias/bix_dark_bias_data_prep.py
bix_analysis_libraries/pero_pipes/__init__.py
bix_analysis_libraries/pero_pipes/data_prep.py
bix_analysis_libraries/pl/__init__.py
bix_analysis_libraries/pl/pl_analysis.py
bix_analysis_libraries/pl/pl_data_prep.py
bix_analysis_libraries/temperature_degradation/__init__.py
bix_analysis_libraries/temperature_degradation/temperature_degradation_data_prep.py
bix_analysis_libraries/xrf/__init__.py
bix_analysis_libraries/xrf/data_prep.py
bix_analysis_libraries-0.1.1.dist-info/LICENSE
bix_analysis_libraries-0.1.1.dist-info/METADATA
bix_analysis_libraries-0.1.1.dist-info/WHEEL
bix_analysis_libraries-0.1.1.dist-info/top_level.txt
bix_analysis_libraries-0.1.1.dist-info/RECORD
