Metadata-Version: 2.1
Name: bix-analysis-libraries
Version: 0.1.1
Summary: An assortment of analysis libraries.
Home-page: https://github.com/vskorjanc/analysis-libraries
Author: Viktor Skorjanc
Author-email: viktor.skorjanc@gmail.com
License: UNKNOWN
Platform: UNKNOWN
Classifier: Programming Language :: Python :: 3
Classifier: License :: OSI Approved :: MIT License
Classifier: Operating System :: OS Independent
License-File: LICENSE
Requires-Dist: bric-analysis-libraries
Requires-Dist: pandas
Requires-Dist: numpy
Requires-Dist: matplotlib
Requires-Dist: scipy
Requires-Dist: plotly
Requires-Dist: thot-data
Requires-Dist: thot-cli
